sourcery-1.43.0.data/purelib/sourcery/_asyncio.pyd
sourcery-1.43.0.data/purelib/sourcery/_bz2.pyd
sourcery-1.43.0.data/purelib/sourcery/_cffi_backend.pyd
sourcery-1.43.0.data/purelib/sourcery/_ctypes.pyd
sourcery-1.43.0.data/purelib/sourcery/_decimal.pyd
sourcery-1.43.0.data/purelib/sourcery/_elementtree.pyd
sourcery-1.43.0.data/purelib/sourcery/_hashlib.pyd
sourcery-1.43.0.data/purelib/sourcery/_lzma.pyd
sourcery-1.43.0.data/purelib/sourcery/_multiprocessing.pyd
sourcery-1.43.0.data/purelib/sourcery/_overlapped.pyd
sourcery-1.43.0.data/purelib/sourcery/_queue.pyd
sourcery-1.43.0.data/purelib/sourcery/_ruamel_yaml.pyd
sourcery-1.43.0.data/purelib/sourcery/_socket.pyd
sourcery-1.43.0.data/purelib/sourcery/_sqlite3.pyd
sourcery-1.43.0.data/purelib/sourcery/_ssl.pyd
sourcery-1.43.0.data/purelib/sourcery/_uuid.pyd
sourcery-1.43.0.data/purelib/sourcery/_zoneinfo.pyd
sourcery-1.43.0.data/purelib/sourcery/languages.so
sourcery-1.43.0.data/purelib/sourcery/libcrypto-3.dll
sourcery-1.43.0.data/purelib/sourcery/libffi-8.dll
sourcery-1.43.0.data/purelib/sourcery/libssl-3.dll
sourcery-1.43.0.data/purelib/sourcery/linguist-languages.yml
sourcery-1.43.0.data/purelib/sourcery/pyexpat.pyd
sourcery-1.43.0.data/purelib/sourcery/pysolvers.pyd
sourcery-1.43.0.data/purelib/sourcery/python3.dll
sourcery-1.43.0.data/purelib/sourcery/python311.dll
sourcery-1.43.0.data/purelib/sourcery/select.pyd
sourcery-1.43.0.data/purelib/sourcery/sourcery.exe
sourcery-1.43.0.data/purelib/sourcery/sqlite3.dll
sourcery-1.43.0.data/purelib/sourcery/ujson.pyd
sourcery-1.43.0.data/purelib/sourcery/unicodedata.pyd
sourcery-1.43.0.data/purelib/sourcery/vcruntime140.dll
sourcery-1.43.0.data/purelib/sourcery/vcruntime140_1.dll
sourcery-1.43.0.data/purelib/sourcery/wrapper.py
sourcery-1.43.0.data/purelib/sourcery/black/_width_table.pyd
sourcery-1.43.0.data/purelib/sourcery/black/brackets.pyd
sourcery-1.43.0.data/purelib/sourcery/black/cache.pyd
sourcery-1.43.0.data/purelib/sourcery/black/comments.pyd
sourcery-1.43.0.dist-info/METADATA
sourcery-1.43.0.dist-info/WHEEL
sourcery-1.43.0.dist-info/entry_points.txt
sourcery-1.43.0.dist-info/top_level.txt
sourcery-1.43.0.dist-info/RECORD
